{"_type":"export","__export_format":4,"__export_date":"2024-04-19T18:53:19.249Z","__export_source":"insomnia.desktop.app:v8.6.1","resources":[{"_id":"req_81d40d95a78440e0a8405f2e472ee514","parentId":"wrk_cc6b1d0f9f9c464baf0ce5e013d3ca5a","modified":1713020095199,"created":1713016161514,"url":"http://localhost:8081/sign-in","name":"Get csrf token","description":"","method":"GET","body":{},"parameters":[],"headers":[{"name":"User-Agent","value":"insomnia/8.6.1"}],"authentication":{"type":"basic","useISO88591":false,"disabled":false,"username":"artem","password":"12345678"},"metaSortKey":-1713016161514,"isPrivate":false,"pathParameters":[],"settingStoreCookies":true,"settingSendCookies":true,"settingDisableRenderRequestBody":false,"settingEncodeUrl":true,"settingRebuildPath":true,"settingFollowRedirects":"global","_type":"request"},{"_id":"wrk_cc6b1d0f9f9c464baf0ce5e013d3ca5a","parentId":null,"modified":1709904641915,"created":1709904641915,"name":"blps","description":"","scope":"collection","_type":"workspace"},{"_id":"req_2d45ef1a73fc4b85a5c1551ab67b4c7f","parentId":"wrk_cc6b1d0f9f9c464baf0ce5e013d3ca5a","modified":1713018442650,"created":1712951550712,"url":"http://localhost:8081/sign-up","name":"SignUp","description":"","method":"POST","body":{"mimeType":"application/json","text":"{\n\t\"username\" : \"courier\",\n\t\"password\" : \"12345678\",\n\t\"role\" : \"Клиент\",\n\t\"fio\" : \"тест\",\n\t\"mail\" : \"тест\",\n\t\"phone\" : \"1\"\n}"},"parameters":[],"headers":[{"name":"Content-Type","value":"application/json"},{"name":"User-Agent","value":"insomnia/8.6.1"}],"authentication":{},"metaSortKey":-1712951550712,"isPrivate":false,"pathParameters":[],"settingStoreCookies":true,"settingSendCookies":true,"settingDisableRenderRequestBody":false,"settingEncodeUrl":true,"settingRebuildPath":true,"settingFollowRedirects":"global","_type":"request"},{"_id":"req_3348b482a3694f8397f83fc4bed78895","parentId":"wrk_cc6b1d0f9f9c464baf0ce5e013d3ca5a","modified":1713551766863,"created":1709995637723,"url":"http://localhost:8081/order/752","name":"Order","description":"","method":"GET","body":{},"parameters":[],"headers":[{"name":"User-Agent","value":"insomnia/8.6.1","id":"pair_963d7b06d9a9449ebe2b88cf55fe76e5"},{"id":"pair_bd188e0222194277b5b09eaaca2d3b52","name":"X-XSRF-TOKEN","value":"","description":""}],"authentication":{"type":"basic","useISO88591":false,"disabled":false,"username":"artem","password":"12345678"},"metaSortKey":-1709972305364.25,"isPrivate":false,"pathParameters":[],"settingStoreCookies":true,"settingSendCookies":true,"settingDisableRenderRequestBody":false,"settingEncodeUrl":true,"settingRebuildPath":true,"settingFollowRedirects":"global","_type":"request"},{"_id":"req_6dd4d334dcbb48b0b2855512a161b4d5","parentId":"wrk_cc6b1d0f9f9c464baf0ce5e013d3ca5a","modified":1713016032053,"created":1709994856548,"url":"http://localhost:8081/order","name":"Orders","description":"","method":"GET","body":{},"parameters":[{"id":"pair_16befb4d54164409b7681571ed0d1fe0","name":"page","value":"1","description":"","disabled":true},{"id":"pair_90b538643269420ebd4c1ec6f1c96f23","name":"size","value":"1","description":"","disabled":true}],"headers":[{"name":"User-Agent","value":"insomnia/8.6.1","id":"pair_f8fedb09fb7e4d8faf010fc2343ebc01"}],"authentication":{"type":"basic","useISO88591":false,"disabled":false,"username":"artem","password":"12345678"},"metaSortKey":-1709970895915.2656,"isPrivate":false,"pathParameters":[],"settingStoreCookies":true,"settingSendCookies":true,"settingDisableRenderRequestBody":false,"settingEncodeUrl":true,"settingRebuildPath":true,"settingFollowRedirects":"global","_type":"request"},{"_id":"req_857b17f7e81747ae8eff40958a6cbf39","parentId":"wrk_cc6b1d0f9f9c464baf0ce5e013d3ca5a","modified":1711178734422,"created":1711178610175,"url":"http://localhost:8081/products/1","name":"Product","description":"","method":"GET","body":{},"parameters":[],"headers":[{"name":"User-Agent","value":"insomnia/8.6.1","id":"pair_963d7b06d9a9449ebe2b88cf55fe76e5"}],"authentication":{"type":"basic","useISO88591":false,"disabled":false,"username":"artem","password":"12345678"},"metaSortKey":-1709969486466.2812,"isPrivate":false,"pathParameters":[],"settingStoreCookies":true,"settingSendCookies":true,"settingDisableRenderRequestBody":false,"settingEncodeUrl":true,"settingRebuildPath":true,"settingFollowRedirects":"global","_type":"request"},{"_id":"req_1a1b1ce5c4db40a08ca48a62f0053978","parentId":"wrk_cc6b1d0f9f9c464baf0ce5e013d3ca5a","modified":1711178624064,"created":1711178617687,"url":"http://localhost:8081/products","name":"Products","description":"","method":"GET","body":{},"parameters":[{"id":"pair_16befb4d54164409b7681571ed0d1fe0","name":"page","value":"1","description":"","disabled":true},{"id":"pair_90b538643269420ebd4c1ec6f1c96f23","name":"size","value":"1","description":"","disabled":true}],"headers":[{"name":"User-Agent","value":"insomnia/8.6.1","id":"pair_f8fedb09fb7e4d8faf010fc2343ebc01"}],"authentication":{"type":"basic","useISO88591":false,"disabled":false,"username":"artem","password":"12345678"},"metaSortKey":-1709963848670.3438,"isPrivate":false,"pathParameters":[],"settingStoreCookies":true,"settingSendCookies":true,"settingDisableRenderRequestBody":false,"settingEncodeUrl":true,"settingRebuildPath":true,"settingFollowRedirects":"global","_type":"request"},{"_id":"req_d44214b8ab974552935ec5f331e35148","parentId":"wrk_cc6b1d0f9f9c464baf0ce5e013d3ca5a","modified":1713013655735,"created":1709995651294,"url":"http://localhost:8081/delivery/102","name":"Delivery","description":"","method":"GET","body":{},"parameters":[],"headers":[{"name":"User-Agent","value":"insomnia/8.6.1"}],"authentication":{"type":"basic","useISO88591":false,"disabled":true,"username":"worker1","password":"12345678"},"metaSortKey":-1709961029772.375,"isPrivate":false,"pathParameters":[],"settingStoreCookies":true,"settingSendCookies":true,"settingDisableRenderRequestBody":false,"settingEncodeUrl":true,"settingRebuildPath":true,"settingFollowRedirects":"global","_type":"request"},{"_id":"req_176e0ff76b5a4ae0913e238b1cef60ad","parentId":"wrk_cc6b1d0f9f9c464baf0ce5e013d3ca5a","modified":1711134712072,"created":1709995028548,"url":"http://localhost:8081/delivery","name":"Deliveries","description":"","method":"GET","body":{},"parameters":[{"id":"pair_16befb4d54164409b7681571ed0d1fe0","name":"page","value":"0","description":"","disabled":true},{"id":"pair_90b538643269420ebd4c1ec6f1c96f23","name":"size","value":"1","description":"","disabled":true}],"headers":[{"name":"User-Agent","value":"insomnia/8.6.1"}],"authentication":{"type":"basic","useISO88591":false,"disabled":false,"username":"courier","password":"12345678"},"metaSortKey":-1709958210874.4062,"isPrivate":false,"pathParameters":[],"settingStoreCookies":true,"settingSendCookies":true,"settingDisableRenderRequestBody":false,"settingEncodeUrl":true,"settingRebuildPath":true,"settingFollowRedirects":"global","_type":"request"},{"_id":"req_a2be96831fed4bd99c700fa824aa3854","parentId":"wrk_cc6b1d0f9f9c464baf0ce5e013d3ca5a","modified":1712961926134,"created":1709995657659,"url":"http://localhost:8081/pickup/1","name":"Pickup","description":"","method":"GET","body":{},"parameters":[],"headers":[{"name":"User-Agent","value":"insomnia/8.6.1"}],"authentication":{"type":"basic","useISO88591":false,"disabled":false,"username":"worker","password":"12345678"},"metaSortKey":-1709955391976.4375,"isPrivate":false,"pathParameters":[],"settingStoreCookies":true,"settingSendCookies":true,"settingDisableRenderRequestBody":false,"settingEncodeUrl":true,"settingRebuildPath":true,"settingFollowRedirects":"global","_type":"request"},{"_id":"req_419fba3516634cc6a9e2560c8cfdc89c","parentId":"wrk_cc6b1d0f9f9c464baf0ce5e013d3ca5a","modified":1712960711252,"created":1709995010286,"url":"http://localhost:8081/pickup","name":"Pickups","description":"","method":"GET","body":{},"parameters":[{"id":"pair_16befb4d54164409b7681571ed0d1fe0","name":"page","value":"0","description":"","disabled":true},{"id":"pair_90b538643269420ebd4c1ec6f1c96f23","name":"size","value":"1","description":"","disabled":true}],"headers":[{"name":"User-Agent","value":"insomnia/8.6.1"}],"authentication":{"type":"basic","useISO88591":false,"disabled":false,"username":"worker","password":"12345678"},"metaSortKey":-1709949754180.5,"isPrivate":false,"pathParameters":[],"settingStoreCookies":true,"settingSendCookies":true,"settingDisableRenderRequestBody":false,"settingEncodeUrl":true,"settingRebuildPath":true,"settingFollowRedirects":"global","_type":"request"},{"_id":"req_7ff99fde12944d2aba9634c308fc75a9","parentId":"wrk_cc6b1d0f9f9c464baf0ce5e013d3ca5a","modified":1713552030076,"created":1709904651813,"url":"http://localhost:8081/order","name":"Add Order","description":"","method":"POST","body":{"mimeType":"application/json","text":"{\n\t\"products\": [\n\t\t{\n\t\t\t\"name\": \"Нитка\",\n\t\t\t\"count\": 10\n\t\t}\n\t]\n}"},"parameters":[],"headers":[{"name":"Content-Type","value":"application/json","id":"pair_e7c1d30bf8444e7face40e0c909fef34"},{"name":"User-Agent","value":"insomnia/8.6.1","id":"pair_3896f3b267cf4f73b53ec412435d19e3"},{"id":"pair_04290303318142cfb4a31cc7230b2fd6","name":"X-XSRF-TOKEN","value":"{{ _.token }}","description":"","disabled":false}],"authentication":{"type":"basic","useISO88591":false,"disabled":false,"username":"artem","password":"12345678"},"metaSortKey":-1709904651813,"isPrivate":false,"pathParameters":[],"settingStoreCookies":true,"settingSendCookies":true,"settingDisableRenderRequestBody":false,"settingEncodeUrl":true,"settingRebuildPath":true,"settingFollowRedirects":"global","_type":"request"},{"_id":"req_674acdb966644862befc03720d32fc2c","parentId":"wrk_cc6b1d0f9f9c464baf0ce5e013d3ca5a","modified":1713552669950,"created":1709918397155,"url":"http://localhost:8081/order/payment","name":"Payment Type","description":"","method":"POST","body":{"mimeType":"application/json","text":"{\n\t\"id\": {{ _.order_id }},\n\t\"type\": \"При получении\"\n}"},"parameters":[],"headers":[{"name":"Content-Type","value":"application/json","id":"pair_4275a00df4e843d0aa4920bdc89e24b5"},{"name":"User-Agent","value":"insomnia/8.6.1","id":"pair_3896f3b267cf4f73b53ec412435d19e3"},{"id":"pair_583e36ffed934c7eb6547be77f725896","name":"X-XSRF-TOKEN","value":"{{ _.token }}","description":""}],"authentication":{"type":"basic","useISO88591":false,"disabled":false,"username":"artem","password":"12345678"},"metaSortKey":-1709904651763,"isPrivate":false,"pathParameters":[],"settingStoreCookies":true,"settingSendCookies":true,"settingDisableRenderRequestBody":false,"settingEncodeUrl":true,"settingRebuildPath":true,"settingFollowRedirects":"global","_type":"request"},{"_id":"req_19d176ae61514c34a6723423eb6203c1","parentId":"wrk_cc6b1d0f9f9c464baf0ce5e013d3ca5a","modified":1713552677214,"created":1709918404712,"url":"http://localhost:8081/order/receiving","name":"Receive Type","description":"","method":"POST","body":{"mimeType":"application/json","text":"{\n\t\"id\": {{ _.order_id }},\n\t\"type\": \"Доставка\",\n\t\"address\": \"1\"\n}"},"parameters":[],"headers":[{"name":"Content-Type","value":"application/json","id":"pair_6812fc7989954a80b35d644e3dda47d7"},{"name":"User-Agent","value":"insomnia/8.6.1","id":"pair_3896f3b267cf4f73b53ec412435d19e3"},{"id":"pair_156aaec0d534412ba1810a54f87a6ad9","name":"X-XSRF-TOKEN","value":"{{ _.token }}","description":""}],"authentication":{"type":"basic","useISO88591":false,"disabled":false,"username":"artem","password":"12345678"},"metaSortKey":-1709904651713,"isPrivate":false,"pathParameters":[],"settingStoreCookies":true,"settingSendCookies":true,"settingDisableRenderRequestBody":false,"settingEncodeUrl":true,"settingRebuildPath":true,"settingFollowRedirects":"global","_type":"request"},{"_id":"req_3bf3313f4f444ea5a0249b968ba38d71","parentId":"wrk_cc6b1d0f9f9c464baf0ce5e013d3ca5a","modified":1713552682264,"created":1709918428192,"url":"http://localhost:8081/order/payment","name":"Pay Online","description":"","method":"PUT","body":{"mimeType":"application/json","text":"{\n\t\"id\": {{ _.order_id }}\n}"},"parameters":[{"id":"pair_8f47c2b16b3d4d72b267bdd8b8608287","name":"id","value":"2","description":"","disabled":true}],"headers":[{"name":"Content-Type","value":"application/json","id":"pair_2cceaa76c7aa45d787d3564d3c62449e"},{"name":"User-Agent","value":"insomnia/8.6.1","id":"pair_3896f3b267cf4f73b53ec412435d19e3"},{"id":"pair_5607fe6ada9f414dbf907df14040acbb","name":"X-XSRF-TOKEN","value":"{{ _.token }}","description":""}],"authentication":{"type":"basic","useISO88591":false,"disabled":false,"username":"artem","password":"12345678"},"metaSortKey":-1709904651663,"isPrivate":false,"pathParameters":[],"settingStoreCookies":true,"settingSendCookies":true,"settingDisableRenderRequestBody":false,"settingEncodeUrl":true,"settingRebuildPath":true,"settingFollowRedirects":"global","_type":"request"},{"_id":"req_7c070b6582034d9f994c21624ec03bca","parentId":"wrk_cc6b1d0f9f9c464baf0ce5e013d3ca5a","modified":1713552685657,"created":1709922718614,"url":"http://localhost:8081/processing","name":"Work","description":"","method":"POST","body":{"mimeType":"application/json","text":"{\n\t\"id\": {{ _.order_id }}\n}"},"parameters":[{"id":"pair_8f47c2b16b3d4d72b267bdd8b8608287","name":"id","value":"2","description":"","disabled":true},{"id":"pair_f97f6f9d9a5248fcaacd6793f689b482","name":"user","value":"2","description":"","disabled":true}],"headers":[{"name":"Content-Type","value":"application/json","id":"pair_da847d370e234cc3a36b4244a3aa3bd5"},{"name":"User-Agent","value":"insomnia/8.6.1","id":"pair_3896f3b267cf4f73b53ec412435d19e3"},{"id":"pair_8336a17c0d9e47e3ac5565b8ea021add","name":"X-XSRF-TOKEN","value":"{{ _.token }}","description":""}],"authentication":{"type":"basic","useISO88591":false,"disabled":false,"username":"worker","password":"12345678"},"metaSortKey":-1709904651613,"isPrivate":false,"pathParameters":[],"settingStoreCookies":true,"settingSendCookies":true,"settingDisableRenderRequestBody":false,"settingEncodeUrl":true,"settingRebuildPath":true,"settingFollowRedirects":"global","_type":"request"},{"_id":"req_feba16467a834a619becb34b27d7b22f","parentId":"wrk_cc6b1d0f9f9c464baf0ce5e013d3ca5a","modified":1713552688960,"created":1709922723780,"url":"http://localhost:8081/processing","name":"Done","description":"","method":"PUT","body":{"mimeType":"application/json","text":"{\n\t\"id\": {{ _.order_id }}\n}"},"parameters":[{"id":"pair_8f47c2b16b3d4d72b267bdd8b8608287","name":"id","value":"2","description":"","disabled":true},{"id":"pair_c6987d732f0e43bd94e5c6a72c3e1978","name":"user","value":"2","description":"","disabled":true}],"headers":[{"name":"Content-Type","value":"application/json","id":"pair_3acadca9252e468fb42a20f92dad7ac2"},{"name":"User-Agent","value":"insomnia/8.6.1","id":"pair_3896f3b267cf4f73b53ec412435d19e3"},{"id":"pair_9768553878b249adb6a3788601334be5","name":"X-XSRF-TOKEN","value":"{{ _.token }}","description":""}],"authentication":{"type":"basic","useISO88591":false,"disabled":false,"username":"worker","password":"12345678"},"metaSortKey":-1709904651563,"isPrivate":false,"pathParameters":[],"settingStoreCookies":true,"settingSendCookies":true,"settingDisableRenderRequestBody":false,"settingEncodeUrl":true,"settingRebuildPath":true,"settingFollowRedirects":"global","_type":"request"},{"_id":"req_7ec9346fe3ee426db3fb3febe853554d","parentId":"wrk_cc6b1d0f9f9c464baf0ce5e013d3ca5a","modified":1713552743202,"created":1709927779996,"url":"http://localhost:8081/delivery","name":"Work delivery","description":"","method":"POST","body":{"mimeType":"application/json","text":"{\n\t\"id\": {{ _.order_id }}\n}"},"parameters":[{"id":"pair_8f47c2b16b3d4d72b267bdd8b8608287","name":"id","value":"2","description":"","disabled":true},{"id":"pair_c6987d732f0e43bd94e5c6a72c3e1978","name":"user","value":"3","description":"","disabled":true}],"headers":[{"name":"Content-Type","value":"application/json","id":"pair_475489a99c3940f1afb723db86d6e1c6"},{"name":"User-Agent","value":"insomnia/8.6.1","id":"pair_3896f3b267cf4f73b53ec412435d19e3"},{"id":"pair_cd0688a7355f45fc9033ec8b93bcded2","name":"X-XSRF-TOKEN","value":"{{ _.token }}","description":""}],"authentication":{"type":"basic","useISO88591":false,"disabled":false,"username":"courier","password":"12345678"},"metaSortKey":-1709904651513,"isPrivate":false,"pathParameters":[],"settingStoreCookies":true,"settingSendCookies":true,"settingDisableRenderRequestBody":false,"settingEncodeUrl":true,"settingRebuildPath":true,"settingFollowRedirects":"global","_type":"request"},{"_id":"req_6dd59a5a1c2e4e65927b15456897ee07","parentId":"wrk_cc6b1d0f9f9c464baf0ce5e013d3ca5a","modified":1713552744947,"created":1709927787073,"url":"http://localhost:8081/delivery","name":"Done delivery","description":"","method":"PUT","body":{"mimeType":"application/json","text":"{\n\t\"id\": {{ _.order_id }}\n}"},"parameters":[{"id":"pair_8f47c2b16b3d4d72b267bdd8b8608287","name":"id","value":"2","description":"","disabled":true},{"id":"pair_c6987d732f0e43bd94e5c6a72c3e1978","name":"user","value":"3","description":"","disabled":true}],"headers":[{"name":"Content-Type","value":"application/json","id":"pair_d724577ad3ef49ed87be39abbb5fb415"},{"name":"User-Agent","value":"insomnia/8.6.1","id":"pair_3896f3b267cf4f73b53ec412435d19e3"},{"id":"pair_0e007c1da8824f4bb3dfe0047f821a1c","name":"X-XSRF-TOKEN","value":"{{ _.token }}","description":""}],"authentication":{"type":"basic","useISO88591":false,"disabled":false,"username":"courier","password":"12345678"},"metaSortKey":-1709904651463,"isPrivate":false,"pathParameters":[],"settingStoreCookies":true,"settingSendCookies":true,"settingDisableRenderRequestBody":false,"settingEncodeUrl":true,"settingRebuildPath":true,"settingFollowRedirects":"global","_type":"request"},{"_id":"req_446c4f5cdffb4320a16253cfdc9e5956","parentId":"wrk_cc6b1d0f9f9c464baf0ce5e013d3ca5a","modified":1713552751692,"created":1709927794929,"url":"http://localhost:8081/delivery/payment","name":"Pay delivery","description":"","method":"POST","body":{"mimeType":"application/json","text":"{\n\t\"id\": {{ _.order_id }}\n}"},"parameters":[{"id":"pair_8f47c2b16b3d4d72b267bdd8b8608287","name":"id","value":"2","description":"","disabled":true},{"id":"pair_c6987d732f0e43bd94e5c6a72c3e1978","name":"user","value":"1","description":"","disabled":true}],"headers":[{"name":"Content-Type","value":"application/json","id":"pair_72e369601aad4da599885cc8cb2d37f2"},{"name":"User-Agent","value":"insomnia/8.6.1","id":"pair_3896f3b267cf4f73b53ec412435d19e3"},{"id":"pair_d834b50a67304c22a790151bb9b65b6c","name":"X-XSRF-TOKEN","value":"{{ _.token }}","description":""}],"authentication":{"type":"basic","useISO88591":false,"disabled":false,"username":"artem","password":"12345678"},"metaSortKey":-1709904651413,"isPrivate":false,"pathParameters":[],"settingStoreCookies":true,"settingSendCookies":true,"settingDisableRenderRequestBody":false,"settingEncodeUrl":true,"settingRebuildPath":true,"settingFollowRedirects":"global","_type":"request"},{"_id":"req_2d303ca93d61497a8eaf449b1698e619","parentId":"wrk_cc6b1d0f9f9c464baf0ce5e013d3ca5a","modified":1713552754380,"created":1709927802787,"url":"http://localhost:8081/delivery/receiving","name":"Get delivery","description":"","method":"POST","body":{"mimeType":"application/json","text":"{\n\t\"id\": {{ _.order_id }}\n}"},"parameters":[{"id":"pair_8f47c2b16b3d4d72b267bdd8b8608287","name":"id","value":"2","description":"","disabled":true},{"id":"pair_c6987d732f0e43bd94e5c6a72c3e1978","name":"user","value":"1","description":"","disabled":true}],"headers":[{"name":"Content-Type","value":"application/json","id":"pair_ba0150b6b01242a7bbb520884eacd393"},{"name":"User-Agent","value":"insomnia/8.6.1","id":"pair_3896f3b267cf4f73b53ec412435d19e3"},{"id":"pair_da7f475398b1416a909948e6ddac8c97","name":"X-XSRF-TOKEN","value":"{{ _.token }}","description":""}],"authentication":{"type":"basic","useISO88591":false,"disabled":false,"username":"artem","password":"12345678"},"metaSortKey":-1709904651363,"isPrivate":false,"pathParameters":[],"settingStoreCookies":true,"settingSendCookies":true,"settingDisableRenderRequestBody":false,"settingEncodeUrl":true,"settingRebuildPath":true,"settingFollowRedirects":"global","_type":"request"},{"_id":"req_2027c4360c3b4e94a5f0093856d88e47","parentId":"wrk_cc6b1d0f9f9c464baf0ce5e013d3ca5a","modified":1713552756689,"created":1709927816692,"url":"http://localhost:8081/pickup","name":"Give pickup","description":"","method":"POST","body":{"mimeType":"application/json","text":"{\n\t\"id\": {{ _.order_id }}\n}"},"parameters":[{"id":"pair_8f47c2b16b3d4d72b267bdd8b8608287","name":"id","value":"2","description":"","disabled":true},{"id":"pair_c6987d732f0e43bd94e5c6a72c3e1978","name":"user","value":"2","description":"","disabled":true}],"headers":[{"name":"Content-Type","value":"application/json","id":"pair_a7ead03adf1241969f69ee9d6849f2f9"},{"name":"User-Agent","value":"insomnia/8.6.1","id":"pair_3896f3b267cf4f73b53ec412435d19e3"},{"id":"pair_752aa6ccafc3472c924fe58d982604fe","name":"X-XSRF-TOKEN","value":"{{ _.token }}","description":""}],"authentication":{"type":"basic","useISO88591":false,"disabled":false,"username":"worker","password":"12345678"},"metaSortKey":-1709904651263,"isPrivate":false,"pathParameters":[],"settingStoreCookies":true,"settingSendCookies":true,"settingDisableRenderRequestBody":false,"settingEncodeUrl":true,"settingRebuildPath":true,"settingFollowRedirects":"global","_type":"request"},{"_id":"req_e0c4a85a403841ae8643dafb25cb0dc9","parentId":"wrk_cc6b1d0f9f9c464baf0ce5e013d3ca5a","modified":1713552759036,"created":1709927810472,"url":"http://localhost:8081/pickup","name":"Get pickup","description":"","method":"PUT","body":{"mimeType":"application/json","text":"{\n\t\"id\": {{ _.order_id }}\n}"},"parameters":[{"id":"pair_8f47c2b16b3d4d72b267bdd8b8608287","name":"id","value":"1","description":"","disabled":true},{"id":"pair_c6987d732f0e43bd94e5c6a72c3e1978","name":"user","value":"1","description":"","disabled":true}],"headers":[{"name":"Content-Type","value":"application/json","id":"pair_3914b17e23ee4b72ac899346a406ad42"},{"name":"User-Agent","value":"insomnia/8.6.1","id":"pair_3896f3b267cf4f73b53ec412435d19e3"},{"id":"pair_b8341edc3b3b4f9b9762649e3fb48c3d","name":"X-XSRF-TOKEN","value":"{{ _.token }}","description":""}],"authentication":{"type":"basic","useISO88591":false,"disabled":false,"username":"artem","password":"12345678"},"metaSortKey":-1709904651163,"isPrivate":false,"pathParameters":[],"settingStoreCookies":true,"settingSendCookies":true,"settingDisableRenderRequestBody":false,"settingEncodeUrl":true,"settingRebuildPath":true,"settingFollowRedirects":"global","_type":"request"},{"_id":"env_c15f6bc6b049e876e357ff04a3ae1380a57c41c2","parentId":"wrk_cc6b1d0f9f9c464baf0ce5e013d3ca5a","modified":1713552632107,"created":1709904641917,"name":"Base Environment","data":{"token":"dLBMOxer-Kh-MXDWHwUZ_X7E7h9F5Z1DH4BQtL2-aodpNIG1RdR0CnaZzZtTUBPjKygtmBv9w31x1vlufLRkht7YWuFeB7WD","order_id":"802"},"dataPropertyOrder":{"&":["token","order_id"]},"color":null,"isPrivate":false,"metaSortKey":1709904641917,"_type":"environment"},{"_id":"jar_c15f6bc6b049e876e357ff04a3ae1380a57c41c2","parentId":"wrk_cc6b1d0f9f9c464baf0ce5e013d3ca5a","modified":1713545644881,"created":1709904641919,"name":"Default Jar","cookies":[{"key":"JSESSIONID","value":"F5524134AAD1BB4174BB6071CE13BF13","domain":"localhost","path":"/","httpOnly":true,"hostOnly":true,"creation":"2024-03-22T17:13:33.451Z","lastAccessed":"2024-04-13T14:49:33.537Z","id":"08512d74-3c4a-47c0-b388-098cf3451872"},{"key":"XSRF-TOKEN","value":"1d81a253-ac54-4ee9-b43d-c442cf0f7346","domain":"localhost","path":"/","hostOnly":true,"creation":"2024-04-13T13:42:54.567Z","lastAccessed":"2024-04-19T16:54:04.880Z","id":"e4e8d1a1-df32-4ec2-8286-3be1c397c530"}],"_type":"cookie_jar"}]}